archivotron/PathGenerator.py
archivotron/__init__.py
archivotron/tests/test_PathGenerator.py
archivotron-0.0.0rc0.dist-info/WHEEL
archivotron-0.0.0rc0.dist-info/METADATA
archivotron-0.0.0rc0.dist-info/RECORD
