Metadata-Version: 2.1
Name: archivotron
Version: 0.0.0rc0
Summary: Scientific data archiving assistant
License: MIT
Author: Joshua Teves
Author-email: joshua.teves@nih.gov
Requires-Python: >=3.6,<4.0
Classifier: License :: OSI Approved :: MIT License
Classifier: Programming Language :: Python :: 3
Classifier: Programming Language :: Python :: 3.10
Classifier: Programming Language :: Python :: 3.6
Classifier: Programming Language :: Python :: 3.7
Classifier: Programming Language :: Python :: 3.8
Classifier: Programming Language :: Python :: 3.9
